zexusdigital/__init__.py
zexusdigital/scraper.py
ZexusDigital-0.1.dist-info/LICENSE
ZexusDigital-0.1.dist-info/METADATA
ZexusDigital-0.1.dist-info/WHEEL
ZexusDigital-0.1.dist-info/top_level.txt
ZexusDigital-0.1.dist-info/RECORD
