Metadata-Version: 2.1
Name: ZexusDigital
Version: 0.1
Summary: Instagram Scraping
Home-page: https://github.com/ZexusDigital/instagram-scraper
Author: Zexus
Author-email: zexusdigital@zexusdigital.com
Classifier: Programming Language :: Python :: 3
Classifier: License :: OSI Approved :: MIT License
Classifier: Operating System :: OS Independent
Requires-Python: >=3.6
License-File: LICENSE
Requires-Dist: requests
Requires-Dist: loguru
Requires-Dist: jmespath
